README.rst
setup.py
ivchepot/__init__.py
ivchepot/__main__.py
ivchepot.egg-info/PKG-INFO
ivchepot.egg-info/SOURCES.txt
ivchepot.egg-info/dependency_links.txt
ivchepot.egg-info/not-zip-safe
ivchepot.egg-info/top_level.txt