Metadata-Version: 1.0
Name: ivchepot
Version: 1.0.0
Summary: Simple TCP Honeypot
Home-page: UNKNOWN
Author: Ivche1337
Author-email: ivchepro@gmail.com
License: MIT
Platform: UNKNOWN
